conversor_andre_conforti/__init__.py
conversor_andre_conforti/comprimento.py
conversor_andre_conforti/temperatura.py
conversor_andre_conforti/utils.py
conversor_andre_conforti-0.0.2.dist-info/METADATA
conversor_andre_conforti-0.0.2.dist-info/WHEEL
conversor_andre_conforti-0.0.2.dist-info/top_level.txt
conversor_andre_conforti-0.0.2.dist-info/RECORD
