Metadata-Version: 2.1
Name: conversor_andre_conforti
Version: 0.0.2
Summary: Pacote simples para conversao de unidades.
Author: Andre Conforti
Author-email: andre.r.m.conforti@gmail.com
